nteu_translation_engine/__init__.py
nteu_translation_engine/engine.py
nteu_translation_engine/pipeline.py
nteu_translation_engine/server.py
nteu_translation_engine-0.4.8.dist-info/METADATA
nteu_translation_engine-0.4.8.dist-info/WHEEL
nteu_translation_engine-0.4.8.dist-info/top_level.txt
nteu_translation_engine-0.4.8.dist-info/RECORD
