Metadata-Version: 2.1
Name: nteu-translation-engine
Version: 0.4.8
Summary: NTEU translation engine
Home-page: https://github.com/Pangeamt/nteu-translation-engine
Author: PangeaMT
Author-email: a.cerda@pangeanic.es
License: MIT
Platform: UNKNOWN
Requires-Dist: aiohttp (==3.6.2)
Requires-Dist: click
Requires-Dist: pangeamt-nlp
Requires-Dist: PyYAML
Requires-Dist: uvloop
